{
    "status": "ELEITO POR MÉDIA", 
    "searchable": [
        "Othelino Neto"
    ], 
    "title": "Deputado Estadual", 
    "image": "http://divulgacand2014.tse.jus.br/divulga-cand-2014/eleicao/2014/UF/MA/foto/100000000353.jpg", 
    "state": "MA", 
    "donations": {
        "COMPANHIA SIDERURGICA VALE DO PINDARE": 80000.0
    }, 
    "party": "PC do B", 
    "fullname": "OTHELINO NOVA ALVES NETO", 
    "total": 161392.96, 
    "election_id": 65065, 
    "similars": [
        "Rodrigo Moraes (PSC, SP) - Deputado Estadual", 
        "João Eudes (PRP, PE) - Deputado Estadual", 
        "Agnelo (PDT, RN) - Deputado Estadual"
    ]
}