{
    "status": "ELEITO POR QP", 
    "searchable": [
        "Felipe Attiê"
    ], 
    "title": "Deputado Estadual", 
    "image": "http://divulgacand2014.tse.jus.br/divulga-cand-2014/eleicao/2014/UF/MG/foto/130000000637.jpg", 
    "state": "MG", 
    "donations": {
        "BANCO BMG SA": 50000.0, 
        "DELTA DMINISTRAÇÃO E PARTICIPAÇÃO LTDA": 20000.0, 
        "LIBE CONSTRUTORA LIMITADA": 19978.0
    }, 
    "party": "PP", 
    "fullname": "FELIPE JOSÉ FONSECA ATTIÊ", 
    "total": 428610.0, 
    "election_id": 11911, 
    "similars": [
        "Gustavo Correa (DEM, MG) - Deputado Estadual"
    ]
}