{
    "status": "ELEITO POR QP", 
    "searchable": [
        "Nininho"
    ], 
    "title": "Deputado Estadual", 
    "image": "http://divulgacand2014.tse.jus.br/divulga-cand-2014/eleicao/2014/UF/MT/foto/110000000376.jpg", 
    "state": "MT", 
    "donations": {
        "ENPA ENGENHARIA E PARCERIA LTDA.": 7500.0
    }, 
    "party": "PR", 
    "fullname": "ONDANIR BORTOLINI", 
    "total": 1342402.3, 
    "election_id": 22345, 
    "similars": [
        "Ságuas Moraes (PT, MT) - Deputado Federal", 
        "Valtenir Pereira (PROS, MT) - Deputado Federal", 
        "Lúdio Cabral (PT, MT) - Governador"
    ]
}