{
    "status": "ELEITO POR MÉDIA", 
    "searchable": [
        "Pastor Carlos Alberto"
    ], 
    "title": "Deputado Estadual", 
    "image": "http://divulgacand2014.tse.jus.br/divulga-cand-2014/eleicao/2014/UF/AM/foto/40000000131.jpg", 
    "state": "AM", 
    "donations": {
        "DIRETÓRIO NACIONAL DO PRB": 29000.0
    }, 
    "party": "PRB", 
    "fullname": "CARLOS ALBERTO DE CASTRO ALMEIDA", 
    "total": 185550.14, 
    "election_id": 10123, 
    "similars": [
        "Roberto Alves (PRB, SP) - Deputado Federal", 
        "Fausto Pinato (PRB, SP) - Deputado Federal"
    ]
}